{
  "text": {
    "hello": 16,
    "there": 51,
    "hi": 17,
    "good": 15,
    "morning": 28,
    "what": 59,
    "s": 38,
    "my": 29,
    "horoscope": 18,
    "for": 11,
    "today": 53,
    "tell": 47,
    "me": 27,
    "tomorrow": 54,
    "can": 7,
    "you": 61,
    "next": 32,
    "week": 58,
    "i": 20,
    "want": 57,
    "to": 52,
    "subscribe": 44,
    "your": 62,
    "service": 41,
    "how": 19,
    "sign": 43,
    "up": 55,
    "the": 50,
    "newsletter": 31,
    "__number__": 0,
    "need": 30,
    "please": 36,
    "is": 21,
    "fortune": 12,
    "give": 14,
    "daily": 10,
    "show": 42,
    "zodiac": 63,
    "aries": 5,
    "am": 3,
    "a": 1,
    "leo": 24,
    "it": 22,
    "cancer": 8,
    "gemini": 13,
    "virgo": 56,
    "belong": 6,
    "taurus": 46,
    "libra": 25,
    "capricorn": 9,
    "aquarius": 4,
    "that": 49,
    "pisces": 35,
    "sagittarius": 39,
    "scorpio": 40,
    "yes": 60,
    "sure": 45,
    "absolutely": 2,
    "no": 33,
    "thanks": 48,
    "not": 34,
    "really": 37,
    "maybe": 26,
    "later": 23
  },
  "intent": {
    "greeting": 4,
    "get_horoscope": 3,
    "subscription": 6,
    "dob_intent": 2,
    "inform_zodiac": 5,
    "affirm": 0,
    "deny": 1
  },
  "response": null,
  "action_name": {
    "action_listen": 7,
    "action_restart": 8,
    "action_session_start": 10,
    "action_default_fallback": 4,
    "action_deactivate_loop": 1,
    "action_revert_fallback_events": 9,
    "action_default_ask_affirmation": 2,
    "action_default_ask_rephrase": 3,
    "action_two_stage_fallback": 11,
    "action_unlikely_intent": 12,
    "action_back": 0,
    "action_extract_slots": 5,
    "action_get_horoscope": 6,
    "utter_affirm": 13,
    "utter_ask_zodiac_sign": 14,
    "utter_goodbye": 15
  },
  "action_text": null,
  "intent_response_key": null
}